{
  "gameObjects": [
    {
      "__Base__instanceID": -341378,
      "name": "ColliderDebug",
      "tag": [],
      "transform": {
        "__Base__instanceID": -341380,
        "position": {
          "x": 0.0,
          "y": 1.7,
          "z": 0.0
        },
        "rotation": {
          "x": 0.0,
          "y": 0.0,
          "z": 0.0,
          "w": 1.0
        },
        "scale": {
          "x": 2.0,
          "y": 1.7,
          "z": 2.0
        },
        "__ID__parentTransform": [
          47144
        ],
        "__ID__children": []
      },
      "components": [
        {
          "__Base__instanceID": -341972,
          "__Base__Component": "ModelRenderer",
          "modelName": "Primitive/Capsule.fbx",
          "shadow": false,
          "wireFrame": true
        }
      ]
    },
    {
      "__Base__instanceID": -327148,
      "name": "mainchar",
      "tag": [],
      "transform": {
        "__Base__instanceID": -327150,
        "position": {
          "x": 8.534589E-09,
          "y": 1.99910577E-08,
          "z": -4.8278963E-09
        },
        "rotation": {
          "x": -0.7071068,
          "y": 5.050991E-13,
          "z": 1.34876164E-08,
          "w": 0.7071067
        },
        "scale": {
          "x": 100.0,
          "y": 100.0,
          "z": 99.9999847
        },
        "__ID__parentTransform": [
          -327066
        ],
        "__ID__children": []
      },
      "components": []
    },
    {
      "__Base__instanceID": -327144,
      "name": "leg_lower.R_end",
      "tag": [],
      "transform": {
        "__Base__instanceID": -327146,
        "position": {
          "x": 0.0,
          "y": 0.00544630038,
          "z": 0.0
        },
        "rotation": {
          "x": 0.0,
          "y": 0.0,
          "z": 0.0,
          "w": 1.0
        },
        "scale": {
          "x": 1.0,
          "y": 1.0,
          "z": 1.0
        },
        "__ID__parentTransform": [
          -327142
        ],
        "__ID__children": []
      },
      "components": []
    },
    {
      "__Base__instanceID": -327140,
      "name": "leg_lower.R",
      "tag": [],
      "transform": {
        "__Base__instanceID": -327142,
        "position": {
          "x": -4.656613E-10,
          "y": 0.005446299,
          "z": 0.0
        },
        "rotation": {
          "x": -0.002490731,
          "y": 0.2605401,
          "z": 0.000922956329,
          "w": 0.9654594
        },
        "scale": {
          "x": 1.00000024,
          "y": 1.00000119,
          "z": 0.9999987
        },
        "__ID__parentTransform": [
          -327138
        ],
        "__ID__children": [
          -327146
        ]
      },
      "components": []
    },
    {
      "__Base__instanceID": -327136,
      "name": "leg_upper.R",
      "tag": [],
      "transform": {
        "__Base__instanceID": -327138,
        "position": {
          "x": 0.00254925224,
          "y": -0.00132407155,
          "z": 0.0003674035
        },
        "rotation": {
          "x": 0.0437471978,
          "y": -0.0724826,
          "z": 0.989582956,
          "w": -0.116439134
        },
        "scale": {
          "x": 1.00000143,
          "y": 0.9999998,
          "z": 1.00000072
        },
        "__ID__parentTransform": [
          -327074
        ],
        "__ID__children": [
          -327142
        ]
      },
      "components": []
    },
    {
      "__Base__instanceID": -327132,
      "name": "leg_lower.L_end",
      "tag": [],
      "transform": {
        "__Base__instanceID": -327134,
        "position": {
          "x": 0.0,
          "y": 0.005446301,
          "z": 0.0
        },
        "rotation": {
          "x": 0.0,
          "y": 0.0,
          "z": 0.0,
          "w": 1.0
        },
        "scale": {
          "x": 1.0,
          "y": 1.0,
          "z": 1.0
        },
        "__ID__parentTransform": [
          -327130
        ],
        "__ID__children": []
      },
      "components": []
    },
    {
      "__Base__instanceID": -327128,
      "name": "leg_lower.L",
      "tag": [],
      "transform": {
        "__Base__instanceID": -327130,
        "position": {
          "x": -3.16649679E-10,
          "y": 0.0054463,
          "z": -2.98023217E-10
        },
        "rotation": {
          "x": -0.304083318,
          "y": -0.106533587,
          "z": 0.132052854,
          "w": 0.9374145
        },
        "scale": {
          "x": 0.9999999,
          "y": 0.9999998,
          "z": 0.9999996
        },
        "__ID__parentTransform": [
          -327126
        ],
        "__ID__children": [
          -327134
        ]
      },
      "components": []
    },
    {
      "__Base__instanceID": -327124,
      "name": "leg_upper.L",
      "tag": [],
      "transform": {
        "__Base__instanceID": -327126,
        "position": {
          "x": -0.00254641729,
          "y": -0.00132568576,
          "z": 0.000367457978
        },
        "rotation": {
          "x": -0.282347381,
          "y": 0.306379229,
          "z": 0.895362556,
          "w": 0.157281831
        },
        "scale": {
          "x": 0.999999464,
          "y": 1.0,
          "z": 1.00000012
        },
        "__ID__parentTransform": [
          -327074
        ],
        "__ID__children": [
          -327130
        ]
      },
      "components": []
    },
    {
      "__Base__instanceID": -327120,
      "name": "head_end",
      "tag": [],
      "transform": {
        "__Base__instanceID": -327122,
        "position": {
          "x": 0.0,
          "y": 0.00483586546,
          "z": 0.0
        },
        "rotation": {
          "x": 0.0,
          "y": 0.0,
          "z": 0.0,
          "w": 1.0
        },
        "scale": {
          "x": 1.0,
          "y": 1.0,
          "z": 1.0
        },
        "__ID__parentTransform": [
          -327118
        ],
        "__ID__children": []
      },
      "components": []
    },
    {
      "__Base__instanceID": -327116,
      "name": "head",
      "tag": [],
      "transform": {
        "__Base__instanceID": -327118,
        "position": {
          "x": 0.0,
          "y": 0.00627080724,
          "z": 3.329478E-10
        },
        "rotation": {
          "x": -0.0565807745,
          "y": -0.05808366,
          "z": -0.0172771383,
          "w": 0.9965573
        },
        "scale": {
          "x": 0.9999998,
          "y": 1.00000012,
          "z": 0.9999998
        },
        "__ID__parentTransform": [
          -327074
        ],
        "__ID__children": [
          -327122
        ]
      },
      "components": []
    },
    {
      "__Base__instanceID": -327112,
      "name": "arm_lower.R_end",
      "tag": [],
      "transform": {
        "__Base__instanceID": -327114,
        "position": {
          "x": 0.0,
          "y": 0.00451607676,
          "z": 0.0
        },
        "rotation": {
          "x": 0.0,
          "y": 0.0,
          "z": 0.0,
          "w": 1.0
        },
        "scale": {
          "x": 1.0,
          "y": 1.0,
          "z": 1.0
        },
        "__ID__parentTransform": [
          -327110
        ],
        "__ID__children": []
      },
      "components": []
    },
    {
      "__Base__instanceID": -327108,
      "name": "arm_lower.R",
      "tag": [],
      "transform": {
        "__Base__instanceID": -327110,
        "position": {
          "x": 4.47034826E-10,
          "y": 0.0045160763,
          "z": 2.66336425E-10
        },
        "rotation": {
          "x": 0.00293511618,
          "y": -4.79989467E-05,
          "z": 0.0007080482,
          "w": 0.99999547
        },
        "scale": {
          "x": 0.99999994,
          "y": 1.00000036,
          "z": 0.9999999
        },
        "__ID__parentTransform": [
          -327106
        ],
        "__ID__children": [
          -327114
        ]
      },
      "components": []
    },
    {
      "__Base__instanceID": -327104,
      "name": "arm_upper.R",
      "tag": [],
      "transform": {
        "__Base__instanceID": -327106,
        "position": {
          "x": 0.00372022274,
          "y": 0.00501932437,
          "z": -0.000596007449
        },
        "rotation": {
          "x": -0.528901637,
          "y": -0.339896441,
          "z": -0.481401026,
          "w": 0.6107263
        },
        "scale": {
          "x": 1.00000012,
          "y": 1.00000012,
          "z": 0.99999994
        },
        "__ID__parentTransform": [
          -327074
        ],
        "__ID__children": [
          -327110
        ]
      },
      "components": []
    },
    {
      "__Base__instanceID": -327100,
      "name": "arm_lower.L_end",
      "tag": [],
      "transform": {
        "__Base__instanceID": -327102,
        "position": {
          "x": 0.0,
          "y": 0.00451608,
          "z": 0.0
        },
        "rotation": {
          "x": 0.0,
          "y": 0.0,
          "z": 0.0,
          "w": 1.0
        },
        "scale": {
          "x": 1.0,
          "y": 1.0,
          "z": 1.0
        },
        "__ID__parentTransform": [
          -327098
        ],
        "__ID__children": []
      },
      "components": []
    },
    {
      "__Base__instanceID": -327096,
      "name": "arm_lower.L",
      "tag": [],
      "transform": {
        "__Base__instanceID": -327098,
        "position": {
          "x": 1.9324943E-10,
          "y": 0.00451608,
          "z": -3.5157427E-10
        },
        "rotation": {
          "x": -0.003236711,
          "y": 0.208326221,
          "z": 0.000434103626,
          "w": 0.978054
        },
        "scale": {
          "x": 0.999999642,
          "y": 1.00000024,
          "z": 0.9999999
        },
        "__ID__parentTransform": [
          -327094
        ],
        "__ID__children": [
          -327102
        ]
      },
      "components": []
    },
    {
      "__Base__instanceID": -327092,
      "name": "arm_upper.L",
      "tag": [],
      "transform": {
        "__Base__instanceID": -327094,
        "position": {
          "x": -0.003721435,
          "y": 0.00504826,
          "z": -0.000127954627
        },
        "rotation": {
          "x": -0.0339982547,
          "y": 0.13081257,
          "z": 0.84529686,
          "w": 0.5169192
        },
        "scale": {
          "x": 1.00000012,
          "y": 0.99999994,
          "z": 0.999999762
        },
        "__ID__parentTransform": [
          -327074
        ],
        "__ID__children": [
          -327098
        ]
      },
      "components": []
    },
    {
      "__Base__instanceID": -327088,
      "name": "apron.R_end",
      "tag": [],
      "transform": {
        "__Base__instanceID": -327090,
        "position": {
          "x": 0.0,
          "y": 0.00483586546,
          "z": 0.0
        },
        "rotation": {
          "x": 0.0,
          "y": 0.0,
          "z": 0.0,
          "w": 1.0
        },
        "scale": {
          "x": 1.0,
          "y": 1.0,
          "z": 1.0
        },
        "__ID__parentTransform": [
          -327086
        ],
        "__ID__children": []
      },
      "components": []
    },
    {
      "__Base__instanceID": -327084,
      "name": "apron.R",
      "tag": [],
      "transform": {
        "__Base__instanceID": -327086,
        "position": {
          "x": 0.00191640086,
          "y": 0.001046052,
          "z": 0.00399985071
        },
        "rotation": {
          "x": -0.0578763224,
          "y": 0.44586584,
          "z": 0.8668755,
          "w": -0.215362266
        },
        "scale": {
          "x": 1.00000024,
          "y": 1.0,
          "z": 1.0
        },
        "__ID__parentTransform": [
          -327074
        ],
        "__ID__children": [
          -327090
        ]
      },
      "components": []
    },
    {
      "__Base__instanceID": -327080,
      "name": "apron.L_end",
      "tag": [],
      "transform": {
        "__Base__instanceID": -327082,
        "position": {
          "x": 0.0,
          "y": 0.004835865,
          "z": 0.0
        },
        "rotation": {
          "x": 0.0,
          "y": 0.0,
          "z": 0.0,
          "w": 1.0
        },
        "scale": {
          "x": 1.0,
          "y": 1.0,
          "z": 1.0
        },
        "__ID__parentTransform": [
          -327078
        ],
        "__ID__children": []
      },
      "components": []
    },
    {
      "__Base__instanceID": -327076,
      "name": "apron.L",
      "tag": [],
      "transform": {
        "__Base__instanceID": -327078,
        "position": {
          "x": -0.00191481214,
          "y": 0.0004884366,
          "z": 0.00417715
        },
        "rotation": {
          "x": -0.0273365118,
          "y": 0.381656051,
          "z": 0.8857118,
          "w": 0.262880176
        },
        "scale": {
          "x": 1.00000167,
          "y": 1.00000024,
          "z": 1.00000012
        },
        "__ID__parentTransform": [
          -327074
        ],
        "__ID__children": [
          -327082
        ]
      },
      "components": []
    },
    {
      "__Base__instanceID": -327072,
      "name": "body_upper",
      "tag": [],
      "transform": {
        "__Base__instanceID": -327074,
        "position": {
          "x": -9.936873E-07,
          "y": 0.00104895444,
          "z": 0.0122707663
        },
        "rotation": {
          "x": 0.6330041,
          "y": 0.0636744,
          "z": 0.03219818,
          "w": 0.7708532
        },
        "scale": {
          "x": 0.9999999,
          "y": 1.00000012,
          "z": 1.0
        },
        "__ID__parentTransform": [
          -327070
        ],
        "__ID__children": [
          -327078,
          -327086,
          -327094,
          -327106,
          -327118,
          -327126,
          -327138
        ]
      },
      "components": []
    },
    {
      "__Base__instanceID": -327068,
      "name": "Armature",
      "tag": [],
      "transform": {
        "__Base__instanceID": -327070,
        "position": {
          "x": 0.0,
          "y": 0.0,
          "z": 0.0
        },
        "rotation": {
          "x": -0.7071068,
          "y": 0.0,
          "z": 0.0,
          "w": 0.7071067
        },
        "scale": {
          "x": 100.0,
          "y": 100.0,
          "z": 100.0
        },
        "__ID__parentTransform": [
          -327066
        ],
        "__ID__children": [
          -327074
        ]
      },
      "components": []
    },
    {
      "__Base__instanceID": -327064,
      "name": "Player",
      "tag": [],
      "transform": {
        "__Base__instanceID": -327066,
        "position": {
          "x": 0.0,
          "y": 0.0,
          "z": 0.0
        },
        "rotation": {
          "x": 0.0,
          "y": 0.0,
          "z": 0.0,
          "w": 1.0
        },
        "scale": {
          "x": 100.0,
          "y": 100.0,
          "z": 100.0
        },
        "__ID__parentTransform": [
          47422
        ],
        "__ID__children": [
          -327070,
          -327150
        ]
      },
      "components": []
    },
    {
      "__Base__instanceID": 47142,
      "name": "Player",
      "tag": [],
      "transform": {
        "__Base__instanceID": 47144,
        "position": {
          "x": 0.0,
          "y": 0.0,
          "z": 0.0
        },
        "rotation": {
          "x": 0.0,
          "y": 0.0,
          "z": 0.0,
          "w": 1.0
        },
        "scale": {
          "x": 1.0,
          "y": 1.0,
          "z": 1.0
        },
        "__ID__parentTransform": [],
        "__ID__children": [
          47368,
          47422,
          -341380
        ]
      },
      "components": [
        {
          "__Base__instanceID": 47150,
          "__Base__Component": "RigidBody",
          "isKinematic": false,
          "useGravity": true,
          "dynamicLock": 56,
          "mass": 40.0,
          "linearDamping": 1.0,
          "angularDamping": 0.05
        },
        {
          "__Base__instanceID": 47152,
          "__Base__Component": "CapsuleCollider",
          "cType": 1,
          "disableQuery": false,
          "disableSimulation": false,
          "isTrigger": false,
          "layer": 0,
          "positionOffset": {
            "x": 0.0,
            "y": 1.7,
            "z": 0.0
          },
          "radius": 1.0,
          "height": 0.700000048
        },
        {
          "__Base__instanceID": 47154,
          "__Base__Component": "Controller",
          "detect": false,
          "moveSpeed": 10.0,
          "sensitivity": 90.0,
          "__ID__playerRigidbody": 47150,
          "__ID__modelCore": 47422,
          "__ID__cameraArm": 47368,
          "__ID__cameraCore": 47312,
          "__ID__animator": 47418
        }
      ]
    },
    {
      "__Base__instanceID": 47156,
      "name": "Directional Light",
      "tag": [],
      "transform": {
        "__Base__instanceID": 47160,
        "position": {
          "x": 0.0,
          "y": 3.0,
          "z": 0.0
        },
        "rotation": {
          "x": 0.408217877,
          "y": -0.234569684,
          "z": 0.109381631,
          "w": 0.8754261
        },
        "scale": {
          "x": 1.0,
          "y": 1.0,
          "z": 1.0
        },
        "__ID__parentTransform": [],
        "__ID__children": []
      },
      "components": [
        {
          "__Base__instanceID": 47162,
          "__Base__Component": "DirectionalLight",
          "ambient": {
            "x": 0.2,
            "y": 0.2,
            "z": 0.2
          },
          "diffuse": {
            "x": 0.5849056,
            "y": 0.444197178,
            "z": 0.444197178
          },
          "specular": {
            "x": 0.6320754,
            "y": 0.5575382,
            "z": 0.5575382
          },
          "range": 0.0,
          "angle": 0.0
        }
      ]
    },
    {
      "__Base__instanceID": 47164,
      "name": "fixedTest2",
      "tag": [],
      "transform": {
        "__Base__instanceID": 47182,
        "position": {
          "x": -5.37999964,
          "y": 13.0800018,
          "z": 21.6
        },
        "rotation": {
          "x": -0.286177784,
          "y": -0.100415982,
          "z": -0.315501362,
          "w": 0.899154
        },
        "scale": {
          "x": 2.0,
          "y": 1.0,
          "z": 2.0
        },
        "__ID__parentTransform": [],
        "__ID__children": []
      },
      "components": [
        {
          "__Base__instanceID": 47176,
          "__Base__Component": "MeshRenderer",
          "meshType": 1,
          "wireFrame": false,
          "shadow": true,
          "textureName": "",
          "r": 0.347098619,
          "g": 0.7543809,
          "b": 0.9811321,
          "a": 0.0
        },
        {
          "__Base__instanceID": 47172,
          "__Base__Component": "BoxCollider",
          "cType": 1,
          "disableQuery": false,
          "disableSimulation": false,
          "isTrigger": false,
          "layer": 0,
          "positionOffset": {
            "x": 0.0,
            "y": 0.0,
            "z": 0.0
          },
          "size": {
            "x": 1.0,
            "y": 1.0,
            "z": 1.0
          }
        },
        {
          "__Base__instanceID": 47184,
          "__Base__Component": "RigidBody",
          "isKinematic": false,
          "useGravity": true,
          "dynamicLock": 0,
          "mass": 40.0,
          "linearDamping": 0.0,
          "angularDamping": 0.05
        },
        {
          "__Base__instanceID": 47166,
          "__Base__Component": "FixedJoint",
          "LocalAnchor": {
            "x": 0.0,
            "y": 0.0,
            "z": 0.0
          },
          "LocalAnchorRotation": {
            "w": 1.0,
            "x": 0.0,
            "y": 0.0,
            "z": 0.0
          },
          "__ID__connectedBody": 47194,
          "connectedLocalAnchor": {
            "x": 1.3621912,
            "y": -2.14194322,
            "z": -1.766785
          },
          "connectedLocalAnchorRotation": {
            "w": 0.6521987,
            "x": 0.6316665,
            "y": 0.417134345,
            "z": 0.04041305
          },
          "breakForce": 3.40282347E+38,
          "breakTorque": 3.40282347E+38,
          "enableCollision": false,
          "enablePreprocessing": true
        }
      ]
    },
    {
      "__Base__instanceID": 47186,
      "name": "fixedTest21",
      "tag": [],
      "transform": {
        "__Base__instanceID": 47202,
        "position": {
          "x": -4.39,
          "y": 12.4000015,
          "z": 18.75
        },
        "rotation": {
          "x": -0.864994049,
          "y": -0.318668425,
          "z": -0.245921329,
          "w": 0.299597353
        },
        "scale": {
          "x": 3.0,
          "y": 2.0,
          "z": 3.0
        },
        "__ID__parentTransform": [],
        "__ID__children": []
      },
      "components": [
        {
          "__Base__instanceID": 47196,
          "__Base__Component": "MeshRenderer",
          "meshType": 1,
          "wireFrame": false,
          "shadow": true,
          "textureName": "",
          "r": 1.0,
          "g": 1.0,
          "b": 1.0,
          "a": 0.0
        },
        {
          "__Base__instanceID": 47190,
          "__Base__Component": "BoxCollider",
          "cType": 1,
          "disableQuery": false,
          "disableSimulation": false,
          "isTrigger": false,
          "layer": 0,
          "positionOffset": {
            "x": 0.0,
            "y": 0.0,
            "z": 0.0
          },
          "size": {
            "x": 1.0,
            "y": 1.0,
            "z": 1.0
          }
        },
        {
          "__Base__instanceID": 47194,
          "__Base__Component": "RigidBody",
          "isKinematic": false,
          "useGravity": true,
          "dynamicLock": 0,
          "mass": 40.0,
          "linearDamping": 0.0,
          "angularDamping": 0.05
        }
      ]
    },
    {
      "__Base__instanceID": 47204,
      "name": "Box",
      "tag": [],
      "transform": {
        "__Base__instanceID": 47214,
        "position": {
          "x": 5.06,
          "y": 1.3,
          "z": 2.83
        },
        "rotation": {
          "x": 0.0,
          "y": 0.0,
          "z": 0.0,
          "w": 1.0
        },
        "scale": {
          "x": 2.0,
          "y": 2.0,
          "z": 2.0
        },
        "__ID__parentTransform": [],
        "__ID__children": []
      },
      "components": [
        {
          "__Base__instanceID": 47216,
          "__Base__Component": "MeshRenderer",
          "meshType": 1,
          "wireFrame": false,
          "shadow": true,
          "textureName": "",
          "r": 0.0,
          "g": 0.0,
          "b": 0.0,
          "a": 0.0
        },
        {
          "__Base__instanceID": 47208,
          "__Base__Component": "BoxCollider",
          "cType": 1,
          "disableQuery": false,
          "disableSimulation": false,
          "isTrigger": false,
          "layer": 0,
          "positionOffset": {
            "x": 0.0,
            "y": 0.0,
            "z": 0.0
          },
          "size": {
            "x": 1.0,
            "y": 1.0,
            "z": 1.0
          }
        },
        {
          "__Base__instanceID": 47206,
          "__Base__Component": "RigidBody",
          "isKinematic": false,
          "useGravity": true,
          "dynamicLock": 0,
          "mass": 40.0,
          "linearDamping": 0.0,
          "angularDamping": 0.5
        }
      ]
    },
    {
      "__Base__instanceID": 47222,
      "name": "fixedTest11",
      "tag": [],
      "transform": {
        "__Base__instanceID": 47238,
        "position": {
          "x": 2.88,
          "y": 11.0600014,
          "z": 18.74
        },
        "rotation": {
          "x": 0.653281569,
          "y": 0.270598,
          "z": 0.65328145,
          "w": 0.270598233
        },
        "scale": {
          "x": 1.0,
          "y": 1.0,
          "z": 1.0
        },
        "__ID__parentTransform": [],
        "__ID__children": []
      },
      "components": [
        {
          "__Base__instanceID": 47232,
          "__Base__Component": "MeshRenderer",
          "meshType": 1,
          "wireFrame": false,
          "shadow": true,
          "textureName": "",
          "r": 1.0,
          "g": 0.334905684,
          "b": 0.334905684,
          "a": 0.0
        },
        {
          "__Base__instanceID": 47226,
          "__Base__Component": "BoxCollider",
          "cType": 1,
          "disableQuery": false,
          "disableSimulation": false,
          "isTrigger": false,
          "layer": 0,
          "positionOffset": {
            "x": 0.0,
            "y": 0.0,
            "z": 0.0
          },
          "size": {
            "x": 1.0,
            "y": 1.0,
            "z": 1.0
          }
        },
        {
          "__Base__instanceID": 47230,
          "__Base__Component": "RigidBody",
          "isKinematic": false,
          "useGravity": true,
          "dynamicLock": 0,
          "mass": 40.0,
          "linearDamping": 0.0,
          "angularDamping": 0.05
        }
      ]
    },
    {
      "__Base__instanceID": 47240,
      "name": "Sound_Effect01",
      "tag": [],
      "transform": {
        "__Base__instanceID": 47246,
        "position": {
          "x": -11.3,
          "y": 7.31356335,
          "z": 1.0
        },
        "rotation": {
          "x": 0.0,
          "y": 0.0,
          "z": 0.0,
          "w": 1.0
        },
        "scale": {
          "x": 1.0,
          "y": 1.0,
          "z": 1.0
        },
        "__ID__parentTransform": [],
        "__ID__children": []
      },
      "components": [
        {
          "__Base__instanceID": 47244,
          "__Base__Component": "AudioSource",
          "__ID__soundTransform": 47246,
          "soundName": "EffectTest002.wav"
        }
      ]
    },
    {
      "__Base__instanceID": 47248,
      "name": "Graund",
      "tag": [],
      "transform": {
        "__Base__instanceID": 47254,
        "position": {
          "x": 0.0,
          "y": -0.5,
          "z": 0.0
        },
        "rotation": {
          "x": 0.0,
          "y": 0.0,
          "z": 0.0,
          "w": 1.0
        },
        "scale": {
          "x": 100.0,
          "y": 1.0,
          "z": 100.0
        },
        "__ID__parentTransform": [],
        "__ID__children": []
      },
      "components": [
        {
          "__Base__instanceID": 47258,
          "__Base__Component": "BoxCollider",
          "cType": 0,
          "disableQuery": false,
          "disableSimulation": false,
          "isTrigger": false,
          "layer": 0,
          "positionOffset": {
            "x": 0.0,
            "y": 0.0,
            "z": 0.0
          },
          "size": {
            "x": 1.0,
            "y": 1.0,
            "z": 1.0
          }
        },
        {
          "__Base__instanceID": 47260,
          "__Base__Component": "MeshRenderer",
          "meshType": 1,
          "wireFrame": false,
          "shadow": false,
          "textureName": "Grid/Grid.jpg",
          "r": 0.0,
          "g": 0.0,
          "b": 0.0,
          "a": 0.0
        }
      ]
    },
    {
      "__Base__instanceID": 47262,
      "name": "test",
      "tag": [],
      "transform": {
        "__Base__instanceID": 47278,
        "position": {
          "x": 12.67,
          "y": 14.4099922,
          "z": 14.91
        },
        "rotation": {
          "x": 0.0,
          "y": 0.0,
          "z": 0.0,
          "w": 1.0
        },
        "scale": {
          "x": 2.0,
          "y": 4.0,
          "z": 2.0
        },
        "__ID__parentTransform": [],
        "__ID__children": []
      },
      "components": [
        {
          "__Base__instanceID": 47276,
          "__Base__Component": "MeshRenderer",
          "meshType": 1,
          "wireFrame": false,
          "shadow": true,
          "textureName": "",
          "r": 0.329411775,
          "g": 0.7372549,
          "b": 0.9607843,
          "a": 0.0
        },
        {
          "__Base__instanceID": 47270,
          "__Base__Component": "BoxCollider",
          "cType": 1,
          "disableQuery": false,
          "disableSimulation": false,
          "isTrigger": false,
          "layer": 0,
          "positionOffset": {
            "x": 0.0,
            "y": 0.0,
            "z": 0.0
          },
          "size": {
            "x": 1.0,
            "y": 1.0,
            "z": 1.0
          }
        },
        {
          "__Base__instanceID": 47266,
          "__Base__Component": "RigidBody",
          "isKinematic": false,
          "useGravity": false,
          "dynamicLock": 0,
          "mass": 40.0,
          "linearDamping": 0.0,
          "angularDamping": 0.05
        },
        {
          "__Base__instanceID": 47282,
          "__Base__Component": "AudioSource",
          "__ID__soundTransform": 47278,
          "soundName": "EffectTest002.wav"
        },
        {
          "__Base__instanceID": 47280,
          "__Base__Component": "AudioTest",
          "__ID__audioSource": 47282
        }
      ]
    },
    {
      "__Base__instanceID": 47284,
      "name": "fixedTest1",
      "tag": [],
      "transform": {
        "__Base__instanceID": 47296,
        "position": {
          "x": 1.48,
          "y": 12.1600018,
          "z": 17.94
        },
        "rotation": {
          "x": 0.0,
          "y": 0.0,
          "z": 0.0,
          "w": 1.0
        },
        "scale": {
          "x": 2.0,
          "y": 2.0,
          "z": 2.0
        },
        "__ID__parentTransform": [],
        "__ID__children": []
      },
      "components": [
        {
          "__Base__instanceID": 47304,
          "__Base__Component": "ModelRenderer",
          "modelName": "Primitive/Sphere.fbx",
          "shadow": true,
          "wireFrame": false
        },
        {
          "__Base__instanceID": 47302,
          "__Base__Component": "SphereCollider",
          "cType": 1,
          "disableQuery": false,
          "disableSimulation": false,
          "isTrigger": false,
          "layer": 0,
          "positionOffset": {
            "x": 0.0,
            "y": 0.0,
            "z": 0.0
          },
          "radius": 0.5
        },
        {
          "__Base__instanceID": 47298,
          "__Base__Component": "RigidBody",
          "isKinematic": false,
          "useGravity": true,
          "dynamicLock": 0,
          "mass": 40.0,
          "linearDamping": 0.0,
          "angularDamping": 0.05
        },
        {
          "__Base__instanceID": 47286,
          "__Base__Component": "FixedJoint",
          "LocalAnchor": {
            "x": 0.0,
            "y": 0.0,
            "z": 0.0
          },
          "LocalAnchorRotation": {
            "w": 1.0,
            "x": 0.0,
            "y": 0.0,
            "z": 0.0
          },
          "__ID__connectedBody": 47230,
          "connectedLocalAnchor": {
            "x": 0.21213381,
            "y": -1.34350276,
            "z": -1.40000057
          },
          "connectedLocalAnchorRotation": {
            "w": -0.270598173,
            "x": 0.653281569,
            "y": 0.270597965,
            "z": 0.6532814
          },
          "breakForce": 20000.0,
          "breakTorque": 3.40282347E+38,
          "enableCollision": false,
          "enablePreprocessing": true
        }
      ]
    },
    {
      "__Base__instanceID": 47306,
      "name": "Camera",
      "tag": [],
      "transform": {
        "__Base__instanceID": 47312,
        "position": {
          "x": 0.0,
          "y": 0.0,
          "z": -15.0
        },
        "rotation": {
          "x": 0.0,
          "y": 0.0,
          "z": 0.0,
          "w": 1.0
        },
        "scale": {
          "x": 1.0,
          "y": 1.0,
          "z": 1.0
        },
        "__ID__parentTransform": [
          47368
        ],
        "__ID__children": []
      },
      "components": [
        {
          "__Base__instanceID": 47316,
          "__Base__Component": "AudioListener",
          "__ID__listenerTransform": 47312
        },
        {
          "__Base__instanceID": 47314,
          "__Base__Component": "Camera",
          "mainCamera": true,
          "cameraNear": 0.3,
          "cameraFar": 1000.0,
          "fieldOfView": 0.7853982
        }
      ]
    },
    {
      "__Base__instanceID": 47318,
      "name": "ballTest",
      "tag": [],
      "transform": {
        "__Base__instanceID": 47338,
        "position": {
          "x": 5.78,
          "y": 17.54,
          "z": 18.9599953
        },
        "rotation": {
          "x": 0.0,
          "y": 0.0,
          "z": -0.382683426,
          "w": 0.923879564
        },
        "scale": {
          "x": 2.0,
          "y": 2.0,
          "z": 2.0
        },
        "__ID__parentTransform": [],
        "__ID__children": []
      },
      "components": [
        {
          "__Base__instanceID": 47336,
          "__Base__Component": "MeshRenderer",
          "meshType": 1,
          "wireFrame": false,
          "shadow": true,
          "textureName": "",
          "r": 0.4009434,
          "g": 1.0,
          "b": 0.8375349,
          "a": 0.0
        },
        {
          "__Base__instanceID": 47330,
          "__Base__Component": "BoxCollider",
          "cType": 1,
          "disableQuery": false,
          "disableSimulation": false,
          "isTrigger": false,
          "layer": 0,
          "positionOffset": {
            "x": 0.0,
            "y": 0.0,
            "z": 0.0
          },
          "size": {
            "x": 1.0,
            "y": 1.0,
            "z": 1.0
          }
        },
        {
          "__Base__instanceID": 47320,
          "__Base__Component": "RigidBody",
          "isKinematic": false,
          "useGravity": true,
          "dynamicLock": 0,
          "mass": 40.0,
          "linearDamping": 0.0,
          "angularDamping": 0.05
        },
        {
          "__Base__instanceID": 47324,
          "__Base__Component": "BallJoint",
          "LocalAnchor": {
            "x": 0.0,
            "y": -1.0,
            "z": 0.0
          },
          "LocalAnchorRotation": {
            "w": -0.707106769,
            "x": 0.0,
            "y": 0.0,
            "z": 0.707106769
          },
          "__ID__connectedBody": 47344,
          "connectedLocalAnchor": {
            "x": -0.0141415633,
            "y": 3.38406229,
            "z": 0.0
          },
          "connectedLocalAnchorRotation": {
            "w": 0.7071068,
            "x": 0.0,
            "y": 0.0,
            "z": -0.7071068
          },
          "useSpring": false,
          "spring": 0.0,
          "damping": 0.0,
          "useLimit": true,
          "swingLimitY": 45.0,
          "swingLimitZ": 45.0,
          "bounciness": 0.0,
          "breakForce": 3.40282347E+38,
          "breakTorque": 3.40282347E+38,
          "enableCollision": false,
          "enablePreprocessing": true
        }
      ]
    },
    {
      "__Base__instanceID": 47340,
      "name": "springTest",
      "tag": [],
      "transform": {
        "__Base__instanceID": 47356,
        "position": {
          "x": 2.69,
          "y": 14.43,
          "z": 18.9599953
        },
        "rotation": {
          "x": 0.0,
          "y": 0.0,
          "z": -0.382683426,
          "w": 0.923879564
        },
        "scale": {
          "x": 2.0,
          "y": 2.0,
          "z": 2.0
        },
        "__ID__parentTransform": [],
        "__ID__children": []
      },
      "components": [
        {
          "__Base__instanceID": 47354,
          "__Base__Component": "MeshRenderer",
          "meshType": 1,
          "wireFrame": false,
          "shadow": true,
          "textureName": "",
          "r": 0.7006628,
          "g": 0.9528302,
          "b": 0.4719206,
          "a": 0.0
        },
        {
          "__Base__instanceID": 47348,
          "__Base__Component": "BoxCollider",
          "cType": 1,
          "disableQuery": false,
          "disableSimulation": false,
          "isTrigger": false,
          "layer": 0,
          "positionOffset": {
            "x": 0.0,
            "y": 0.0,
            "z": 0.0
          },
          "size": {
            "x": 1.0,
            "y": 1.0,
            "z": 1.0
          }
        },
        {
          "__Base__instanceID": 47344,
          "__Base__Component": "RigidBody",
          "isKinematic": false,
          "useGravity": true,
          "dynamicLock": 0,
          "mass": 40.0,
          "linearDamping": 0.0,
          "angularDamping": 0.05
        },
        {
          "__Base__instanceID": 47360,
          "__Base__Component": "DistanceJoint",
          "LocalAnchor": {
            "x": 1.0,
            "y": 0.0,
            "z": 0.0
          },
          "LocalAnchorRotation": {
            "w": 1.0,
            "x": 0.0,
            "y": 0.0,
            "z": 0.0
          },
          "__ID__connectedBody": 47230,
          "connectedLocalAnchor": {
            "x": 0.5,
            "y": 0.0,
            "z": 0.0
          },
          "connectedLocalAnchorRotation": {
            "w": 1.0,
            "x": 0.0,
            "y": 0.0,
            "z": 0.0
          },
          "useMinDistance": true,
          "minDistance": 0.0,
          "maxDistance": 4.0,
          "Tolerance": 0.025,
          "breakForce": 3.40282347E+38,
          "breakTorque": 3.40282347E+38,
          "enableCollision": false,
          "enablePreprocessing": true
        },
        {
          "__Base__instanceID": 47358,
          "__Base__Component": "SpringJoint",
          "LocalAnchor": {
            "x": -1.0,
            "y": 0.0,
            "z": 0.0
          },
          "LocalAnchorRotation": {
            "w": 1.0,
            "x": 0.0,
            "y": 0.0,
            "z": 0.0
          },
          "__ID__connectedBody": 47194,
          "connectedLocalAnchor": {
            "x": 1.5,
            "y": 0.0,
            "z": 0.0
          },
          "connectedLocalAnchorRotation": {
            "w": 1.0,
            "x": 0.0,
            "y": 0.0,
            "z": 0.0
          },
          "useSpring": true,
          "spring": 100.0,
          "damper": 10.0,
          "useMinDistance": true,
          "minDistance": 4.0,
          "useMaxDistance": true,
          "maxDistance": 6.0,
          "Tolerance": 0.025,
          "breakForce": 3.40282347E+38,
          "breakTorque": 3.40282347E+38,
          "enableCollision": false,
          "enablePreprocessing": true
        }
      ]
    },
    {
      "__Base__instanceID": 47366,
      "name": "CameraArm",
      "tag": [],
      "transform": {
        "__Base__instanceID": 47368,
        "position": {
          "x": 0.0,
          "y": 3.0,
          "z": 0.0
        },
        "rotation": {
          "x": 0.0,
          "y": 0.0,
          "z": 0.0,
          "w": 1.0
        },
        "scale": {
          "x": 1.0,
          "y": 1.0,
          "z": 1.0
        },
        "__ID__parentTransform": [
          47144
        ],
        "__ID__children": [
          47312
        ]
      },
      "components": []
    },
    {
      "__Base__instanceID": 47370,
      "name": "slideTest",
      "tag": [],
      "transform": {
        "__Base__instanceID": 47388,
        "position": {
          "x": 4.10999966,
          "y": 19.230011,
          "z": 18.9599953
        },
        "rotation": {
          "x": 0.0,
          "y": 0.0,
          "z": -0.382683426,
          "w": 0.923879564
        },
        "scale": {
          "x": 2.0,
          "y": 2.0,
          "z": 2.0
        },
        "__ID__parentTransform": [],
        "__ID__children": []
      },
      "components": [
        {
          "__Base__instanceID": 47386,
          "__Base__Component": "MeshRenderer",
          "meshType": 1,
          "wireFrame": false,
          "shadow": true,
          "textureName": "",
          "r": 0.4009434,
          "g": 1.0,
          "b": 0.8375349,
          "a": 0.0
        },
        {
          "__Base__instanceID": 47380,
          "__Base__Component": "BoxCollider",
          "cType": 1,
          "disableQuery": false,
          "disableSimulation": false,
          "isTrigger": false,
          "layer": 0,
          "positionOffset": {
            "x": 0.0,
            "y": 0.0,
            "z": 0.0
          },
          "size": {
            "x": 1.0,
            "y": 1.0,
            "z": 1.0
          }
        },
        {
          "__Base__instanceID": 47376,
          "__Base__Component": "RigidBody",
          "isKinematic": true,
          "useGravity": false,
          "dynamicLock": 0,
          "mass": 40.0,
          "linearDamping": 0.0,
          "angularDamping": 0.05
        },
        {
          "__Base__instanceID": 47372,
          "__Base__Component": "SlideJoint",
          "LocalAnchor": {
            "x": 0.5,
            "y": 0.0,
            "z": 0.0
          },
          "LocalAnchorRotation": {
            "w": 1.0,
            "x": 0.0,
            "y": 0.0,
            "z": 0.0
          },
          "__ID__connectedBody": 47320,
          "connectedLocalAnchor": {
            "x": -1.87588537,
            "y": 0.0141494693,
            "z": 0.0
          },
          "connectedLocalAnchorRotation": {
            "w": 1.0,
            "x": 0.0,
            "y": 0.0,
            "z": 0.0
          },
          "useSpring": false,
          "spring": 10.0,
          "damper": 0.2,
          "useLimit": true,
          "useMinDistance": true,
          "minDistance": 0.01,
          "useMaxDistance": true,
          "maxDistance": 5.0,
          "bounciness": 0.0,
          "breakForce": 3.40282347E+38,
          "breakTorque": 3.40282347E+38,
          "enableCollision": false,
          "enablePreprocessing": true
        }
      ]
    },
    {
      "__Base__instanceID": 47390,
      "name": "hingeTest",
      "tag": [],
      "transform": {
        "__Base__instanceID": 47408,
        "position": {
          "x": 12.74,
          "y": 17.4800014,
          "z": 14.91
        },
        "rotation": {
          "x": 0.0,
          "y": 0.0,
          "z": 0.0,
          "w": 1.0
        },
        "scale": {
          "x": 2.0,
          "y": 2.0,
          "z": 2.0
        },
        "__ID__parentTransform": [],
        "__ID__children": []
      },
      "components": [
        {
          "__Base__instanceID": 47402,
          "__Base__Component": "BoxCollider",
          "cType": 1,
          "disableQuery": false,
          "disableSimulation": false,
          "isTrigger": false,
          "layer": 0,
          "positionOffset": {
            "x": 0.0,
            "y": 0.0,
            "z": 0.0
          },
          "size": {
            "x": 1.0,
            "y": 1.0,
            "z": 1.0
          }
        },
        {
          "__Base__instanceID": 47398,
          "__Base__Component": "RigidBody",
          "isKinematic": true,
          "useGravity": false,
          "dynamicLock": 0,
          "mass": 40.0,
          "linearDamping": 0.0,
          "angularDamping": 0.05
        },
        {
          "__Base__instanceID": 47394,
          "__Base__Component": "HingeJoint",
          "LocalAnchor": {
            "x": 0.0,
            "y": 0.0,
            "z": 0.0
          },
          "LocalAnchorRotation": {
            "w": -0.707106769,
            "x": 0.0,
            "y": 0.707106769,
            "z": 0.0
          },
          "__ID__connectedBody": 47266,
          "connectedLocalAnchor": {
            "x": 0.0699996948,
            "y": 3.07000923,
            "z": 0.0
          },
          "connectedLocalAnchorRotation": {
            "w": 0.7071068,
            "x": 0.0,
            "y": -0.7071067,
            "z": 0.0
          },
          "useSpring": false,
          "spring": 0.0,
          "damper": 0.0,
          "targetPosition": 0.0,
          "setMotor": true,
          "velocity": -5.0,
          "force": 50.0,
          "freeSpin": true,
          "useLimit": false,
          "angleLower": 0.0,
          "angleUpper": 0.0,
          "bounciness": 0.0,
          "bounceThreshold": 0.5,
          "breakForce": 3.40282347E+38,
          "breakTorque": 3.40282347E+38,
          "enableCollision": false,
          "enablePreprocessing": true
        },
        {
          "__Base__instanceID": 47410,
          "__Base__Component": "ModelRenderer",
          "modelName": "Primitive/Sphere.fbx",
          "shadow": true,
          "wireFrame": false
        }
      ]
    },
    {
      "__Base__instanceID": 47412,
      "name": "Model",
      "tag": [],
      "transform": {
        "__Base__instanceID": 47414,
        "position": {
          "x": 0.0,
          "y": 10.0,
          "z": 0.0
        },
        "rotation": {
          "x": 0.0,
          "y": 1.0,
          "z": 0.0,
          "w": 0.0
        },
        "scale": {
          "x": 1.0,
          "y": 1.0,
          "z": 1.0
        },
        "__ID__parentTransform": [
          47422
        ],
        "__ID__children": []
      },
      "components": [
        {
          "__Base__instanceID": 47416,
          "__Base__Component": "ModelRenderer",
          "modelName": "Player/Player.fbx",
          "shadow": true,
          "wireFrame": false
        },
        {
          "__Base__instanceID": 47418,
          "__Base__Component": "Animator",
          "playWithStart": true,
          "playWithStartAnimationName": "Armature|Armature|Armature|idle",
          "animationBlend": true,
          "animationSetting": [
            {
              "animationName": "Armature|Armature|Armature|attack",
              "playSpeed": 1.0,
              "loop": false
            },
            {
              "animationName": "Armature|Armature|Armature|attack2",
              "playSpeed": 1.0,
              "loop": false
            },
            {
              "animationName": "Armature|Armature|Armature|damage",
              "playSpeed": 1.0,
              "loop": false
            },
            {
              "animationName": "Armature|Armature|Armature|dash",
              "playSpeed": 1.0,
              "loop": false
            },
            {
              "animationName": "Armature|Armature|Armature|down",
              "playSpeed": 1.0,
              "loop": false
            },
            {
              "animationName": "Armature|Armature|Armature|idle",
              "playSpeed": 1.0,
              "loop": true
            },
            {
              "animationName": "Armature|Armature|Armature|Phase3_Player",
              "playSpeed": 1.0,
              "loop": false
            },
            {
              "animationName": "Armature|Armature|Armature|running",
              "playSpeed": 1.0,
              "loop": true
            }
          ],
          "blendSetting": [
            {
              "firstAnimationName": "Armature|Armature|Armature|idle",
              "secondAnimationName": "Armature|Armature|Armature|running",
              "blendTime": 0.1
            },
            {
              "firstAnimationName": "Armature|Armature|Armature|running",
              "secondAnimationName": "Armature|Armature|Armature|idle",
              "blendTime": 0.1
            }
          ]
        }
      ]
    },
    {
      "__Base__instanceID": 47420,
      "name": "Body",
      "tag": [],
      "transform": {
        "__Base__instanceID": 47422,
        "position": {
          "x": 0.0,
          "y": 0.0,
          "z": 0.0
        },
        "rotation": {
          "x": 0.0,
          "y": 0.0,
          "z": 0.0,
          "w": 1.0
        },
        "scale": {
          "x": 0.01,
          "y": 0.01,
          "z": 0.01
        },
        "__ID__parentTransform": [
          47144
        ],
        "__ID__children": [
          -327066,
          47414
        ]
      },
      "components": []
    }
  ]
}